cdk_recaptcha_authorizer/__init__.py
cdk_recaptcha_authorizer/py.typed
cdk_recaptcha_authorizer/_jsii/__init__.py
cdk_recaptcha_authorizer/_jsii/cdk-recaptcha-authorizer@2.2.2.jsii.tgz
cdk_recaptcha_authorizer-2.2.2.dist-info/LICENSE
cdk_recaptcha_authorizer-2.2.2.dist-info/METADATA
cdk_recaptcha_authorizer-2.2.2.dist-info/WHEEL
cdk_recaptcha_authorizer-2.2.2.dist-info/top_level.txt
cdk_recaptcha_authorizer-2.2.2.dist-info/RECORD
