Metadata-Version: 2.1
Name: cdk-recaptcha-authorizer
Version: 2.2.2
Summary: An AWS CDK construct library that provides a reCaptcha Authorizer for API Gateway REST APIs
Home-page: https://constructs.dev/packages/cdk-recaptcha-authorizer
Author: Aaron Lucia
License: Apache-2.0
Project-URL: Source, https://github.com/engineal/cdk-recaptcha-authorizer.git
Platform: UNKNOWN
Classifier: Intended Audience :: Developers
Classifier: Operating System :: OS Independent
Classifier: Programming Language :: JavaScript
Classifier: Programming Language :: Python :: 3 :: Only
Classifier: Programming Language :: Python :: 3.7
Classifier: Programming Language :: Python :: 3.8
Classifier: Programming Language :: Python :: 3.9
Classifier: Programming Language :: Python :: 3.10
Classifier: Programming Language :: Python :: 3.11
Classifier: Typing :: Typed
Classifier: Development Status :: 4 - Beta
Classifier: License :: OSI Approved
Requires-Python: ~=3.7
License-File: LICENSE
Requires-Dist: aws-cdk-lib (==2.77.0)
Requires-Dist: constructs (<11.0.0,>=10.0.0)
Requires-Dist: jsii (<2.0.0,>=1.80.0)
Requires-Dist: publication (>=0.0.3)
Requires-Dist: typeguard (~=2.13.3)
